aws_cdk/__init__.py
aws_cdk/py.typed
aws_cdk/_jsii/__init__.py
aws_cdk/_jsii/aws-cdk-lib@2.236.0.jsii.tgz
aws_cdk/alexa_ask/__init__.py
aws_cdk/assertions/__init__.py
aws_cdk/aws_accessanalyzer/__init__.py
aws_cdk/aws_acmpca/__init__.py
aws_cdk/aws_aiops/__init__.py
aws_cdk/aws_amazonmq/__init__.py
aws_cdk/aws_amplify/__init__.py
aws_cdk/aws_amplifyuibuilder/__init__.py
aws_cdk/aws_apigateway/__init__.py
aws_cdk/aws_apigatewayv2/__init__.py
aws_cdk/aws_apigatewayv2_authorizers/__init__.py
aws_cdk/aws_apigatewayv2_integrations/__init__.py
aws_cdk/aws_appconfig/__init__.py
aws_cdk/aws_appflow/__init__.py
aws_cdk/aws_appintegrations/__init__.py
aws_cdk/aws_applicationautoscaling/__init__.py
aws_cdk/aws_applicationinsights/__init__.py
aws_cdk/aws_applicationsignals/__init__.py
aws_cdk/aws_appmesh/__init__.py
aws_cdk/aws_apprunner/__init__.py
aws_cdk/aws_appstream/__init__.py
aws_cdk/aws_appsync/__init__.py
aws_cdk/aws_apptest/__init__.py
aws_cdk/aws_aps/__init__.py
aws_cdk/aws_arcregionswitch/__init__.py
aws_cdk/aws_arczonalshift/__init__.py
aws_cdk/aws_athena/__init__.py
aws_cdk/aws_auditmanager/__init__.py
aws_cdk/aws_autoscaling/__init__.py
aws_cdk/aws_autoscaling_common/__init__.py
aws_cdk/aws_autoscaling_hooktargets/__init__.py
aws_cdk/aws_autoscalingplans/__init__.py
aws_cdk/aws_b2bi/__init__.py
aws_cdk/aws_backup/__init__.py
aws_cdk/aws_backupgateway/__init__.py
aws_cdk/aws_batch/__init__.py
aws_cdk/aws_bcmdataexports/__init__.py
aws_cdk/aws_bedrock/__init__.py
aws_cdk/aws_bedrockagentcore/__init__.py
aws_cdk/aws_billingconductor/__init__.py
aws_cdk/aws_budgets/__init__.py
aws_cdk/aws_cases/__init__.py
aws_cdk/aws_cassandra/__init__.py
aws_cdk/aws_ce/__init__.py
aws_cdk/aws_certificatemanager/__init__.py
aws_cdk/aws_chatbot/__init__.py
aws_cdk/aws_cleanrooms/__init__.py
aws_cdk/aws_cleanroomsml/__init__.py
aws_cdk/aws_cloud9/__init__.py
aws_cdk/aws_cloudformation/__init__.py
aws_cdk/aws_cloudfront/__init__.py
aws_cdk/aws_cloudfront/experimental/__init__.py
aws_cdk_lib-2.236.0.dist-info/LICENSE
aws_cdk_lib-2.236.0.dist-info/METADATA
aws_cdk_lib-2.236.0.dist-info/NOTICE
aws_cdk_lib-2.236.0.dist-info/WHEEL
aws_cdk_lib-2.236.0.dist-info/top_level.txt
aws_cdk_lib-2.236.0.dist-info/RECORD
