Metadata-Version: 2.1
Name: aws-cdk-lib
Version: 2.236.0
Summary: Version 2 of the AWS Cloud Development Kit library
Home-page: https://github.com/aws/aws-cdk
Author: Amazon Web Services
License: Apache-2.0
Project-URL: Source, https://github.com/aws/aws-cdk.git
Classifier: Intended Audience :: Developers
Classifier: Operating System :: OS Independent
Classifier: Programming Language :: JavaScript
Classifier: Programming Language :: Python :: 3 :: Only
Classifier: Programming Language :: Python :: 3.9
Classifier: Programming Language :: Python :: 3.10
Classifier: Programming Language :: Python :: 3.11
Classifier: Typing :: Typed
Classifier: Development Status :: 5 - Production/Stable
Classifier: License :: OSI Approved
Requires-Python: ~=3.9
License-File: LICENSE
License-File: NOTICE
Requires-Dist: aws-cdk.asset-awscli-v1 ==2.2.263
Requires-Dist: aws-cdk.asset-node-proxy-agent-v6 <3.0.0,>=2.1.0
Requires-Dist: aws-cdk.cloud-assembly-schema <49.0.0,>=48.20.0
Requires-Dist: constructs <11.0.0,>=10.0.0
Requires-Dist: jsii <2.0.0,>=1.125.0
Requires-Dist: publication >=0.0.3
Requires-Dist: typeguard ==2.13.3
